{
    "openlmisUser.basicInformation": "基本信息",
    "openlmisUser.username": "用户名",
    "openlmisUser.firstName": "名字",
    "openlmisUser.lastName": "姓氏",
    "openlmisUser.email": "邮箱",
    "openlmisUser.jobTitle": "职称",
    "openlmisUser.homeFacility": "所属站点",
    "openlmisUser.phoneNumber": "电话号码",
    "openlmisUser.profile": "资料",
    "openlmisUser.roleAssignments": "角色分配",
    "openlmisUser.cancel": "取消",
    "openlmisUser.cancel.restoreSuccessful": "基本信息恢复成功",
    "openlmisUser.cancel.restoreFailed": "基本信息恢复失败",
    "openlmisUser.updateProfile": "更新用户档案",
    "openlmisUser.updateProfile.updateSuccessful": "基本信息更新成功",
    "openlmisUser.updateProfile.updateFailed": "无法更新基本信息",
    "openlmisUser.changePassword": "更改密码",
    "openlmisUser.passwordResetAlert.title": "密码重置成功",
    "openlmisUser.passwordResetAlert.message": "您将退出系统",
    "openlmisUser.passwordResetAlert.label": "登出",
    "openlmisUser.emailVerified": "邮箱已验证",
    "openlmisUser.allowNotifications": "允许通知",
    "openlmisUser.allowNotifications.description.checked": "已选中=您将收到系统中所有的通知（取决于您的角色）",
    "openlmisUser.allowNotifications.description.unchecked": "未选中 = 您将不会收到此类通知",
    "openlmisUser.sendVerificationEmail": "发送验证电子邮件",
    "openlmisUser.sendVerificationEmail.success": "验证邮件已成功发送",
    "openlmisUser.pendingVerificationEmail.info": "电子邮件地址已更改为${email}，正在等待验证",
    "openlmisUser.userProfile": "用户档案",
    "openlmisUser.notificationSettings": "通知设置",
    "openlmisUser.notification": "通知",
    "openlmisUser.noDigestConfigurations": "未找到摘要配置",
    "openlmisUser.userSubscriptionsHaveBeenUpdatedSuccessfully": "用户订阅已成功更新",
    "openlmisUser.failedToUpdateUserSubscriptions": "无法更新用户订阅",
    "openlmisUser.updateSubscriptions": "更新订阅",
    "openlmisUser.schedule": "计划",
    "openlmisUser.useDigest": "使用摘要",
    "openlmisUser.channel": "渠道",
    "openlmisUser.sms": "短信",
    "openlmisUser.onlyEmailChannelIsSupportedForDigestMessage": "摘要消息仅支持通过电子邮件发送"
}
