{
    "adminIsaManage.isa": "目标库存量",
    "adminIsaManage.manageIsa": "管理目标库存量",
    "adminIsaManage.export": "导出",
    "adminIsaManage.viewIsaAsCsv": "以CSV格式查看当前的目标库存量",
    "adminIsaManage.fileIsNotSelected": "未选择文件",
    "adminIsaManage.uploadFailed": "上传失败!",
    "adminIsaManage.csvFile": "CSV 文件",
    "adminIsaManage.upload": "上传",
    "adminIsaManage.uploadSuccess": "文件上传成功。已处理的记录数量：${amount}",
    "adminIsaManage.isaUploadDescription": "更新目标库存量的数值的步骤:\n\n1。点击导出按键下载当前数值.\n2.编辑.csv文件并另存为.csv file.\n3。点击上传并选择已保存的.csv 文件，将更新的版本上传至系统.\n4.。系统将验证该文件是否为.csv格式且带有正确的栏标题。.\nIf文件若上传成功，系统将完成修改。.\nIf文件若上传失败，页面将会显示错误信息。"
}
